mind_randgen_sdk/__init__.py
mind_randgen_sdk/config.py
mind_randgen_sdk/hot_wallet.py
mind_randgen_sdk/randgen_lib.py
mind_randgen_sdk/contracts/__init__.py
mind_randgen_sdk/contracts/fhe_key_registry.py
mind_randgen_sdk/contracts/member_pool.py
mind_randgen_sdk/contracts/randgen_hub.py
mind_randgen_sdk/contracts/util.py
mind_randgen_sdk/contracts/abi/FheKeyRegistry.json
mind_randgen_sdk/contracts/abi/MemberPool.json
mind_randgen_sdk/contracts/abi/RandgenHub.json
mind_randgen_sdk/fhe/__init__.py
mind_randgen_sdk/fhe/fhe.py
mind_randgen_sdk/fhe/fhe_client.py
mind_randgen_sdk/fhe/librandgen_voter.so
mind_randgen_sdk-0.9.3.dist-info/LICENSE
mind_randgen_sdk-0.9.3.dist-info/METADATA
mind_randgen_sdk-0.9.3.dist-info/WHEEL
mind_randgen_sdk-0.9.3.dist-info/top_level.txt
mind_randgen_sdk-0.9.3.dist-info/RECORD
