Metadata-Version: 2.1
Name: mind-randgen-sdk
Version: 0.9.3
Summary: Python SDK for Mind Network Randgen Hub FHE voting
Home-page: https://github.com/mind-network/mind-sdk-randgen-py
Author: Mind Network
Author-email: dev@mindnetwork.xyz
License: UNKNOWN
Platform: UNKNOWN
Classifier: Programming Language :: Python :: 3
Classifier: License :: OSI Approved :: MIT License
Classifier: Operating System :: OS Independent
Requires-Python: >=3.10
License-File: LICENSE
Requires-Dist: cffi<2.0.0,>=1.17.1
Requires-Dist: requests<3.0.0,>=2.32.3
Requires-Dist: typer<1.0.0,>=0.15.1
Requires-Dist: web3<8.0.0,>=7.7.0
